{
	"variants": {
		"facing=north,lit=false": {
			"model": "hemomancy:block/iron_brazier"
		},
		"facing=south,lit=false": {
			"model": "hemomancy:block/iron_brazier",
			"y": 180
		},
		"facing=west,lit=false": {
			"model": "hemomancy:block/iron_brazier",
			"y": 270
		},
		"facing=east,lit=false": {
			"model": "hemomancy:block/iron_brazier",
			"y": 90
		},
		"facing=north,lit=true": {
			"model": "hemomancy:block/iron_brazier_lit"
		},
		"facing=south,lit=true": {
			"model": "hemomancy:block/iron_brazier_lit",
			"y": 180
		},
		"facing=west,lit=true": {
			"model": "hemomancy:block/iron_brazier_lit",
			"y": 270
		},
		"facing=east,lit=true": {
			"model": "hemomancy:block/iron_brazier_lit",
			"y": 90
		}
	}
}